svgpath/__init__.py
svgpath/converter.py
svgpath/functions.py
svgpath/peg.py
svgpath/plot.py
svgpath/symbols.py
svgpath/transforms.py
mountain_svgpath-1.0.1.dist-info/LICENSE
mountain_svgpath-1.0.1.dist-info/METADATA
mountain_svgpath-1.0.1.dist-info/WHEEL
mountain_svgpath-1.0.1.dist-info/entry_points.txt
mountain_svgpath-1.0.1.dist-info/top_level.txt
mountain_svgpath-1.0.1.dist-info/RECORD
