Metadata-Version: 2.1
Name: mountain-svgpath
Version: 1.0.1
Summary: Parse SVG files to numpy vectors
Author: Raub Camaioni
Maintainer: Raub Camaioni
License: The MIT License (MIT)
Project-URL: Homepage, https://github.com/RaubCamaioni/svgpath
Keywords: svg,numpy
Requires-Python: >=3.8
License-File: LICENSE
Requires-Dist: numpy
Requires-Dist: pyparsing >=3.0
Provides-Extra: dev
Requires-Dist: pytest >=6.2.4 ; extra == 'dev'
Requires-Dist: pre-commit ; extra == 'dev'
Provides-Extra: display
Requires-Dist: pyqt6 ; extra == 'display'
Requires-Dist: matplotlib ; extra == 'display'
Provides-Extra: testing
Requires-Dist: pytest >=6.2.4 ; extra == 'testing'
